abp/__init__.py
abp/__main__.py
abp/cli.py
abp/core.py
abp/ui.py
abp/static/app.css
abp/static/app.js
abp/templates/index.html
audio_batch_processor-0.3.0.dist-info/METADATA
audio_batch_processor-0.3.0.dist-info/RECORD
audio_batch_processor-0.3.0.dist-info/WHEEL
audio_batch_processor-0.3.0.dist-info/entry_points.txt
audio_batch_processor-0.3.0.dist-info/top_level.txt
