Metadata-Version: 2.1
Name: audio-batch-processor
Version: 0.3.0
Summary: Batch tool for processing audio files.
Home-page: https://github.com/kkujawinski/audio-batch-processor
Author: Kamil Kujawinski
Author-email: kamil@kujawinski.net
License: GNU GPLv3
Platform: UNKNOWN
Classifier: Development Status :: 5 - Production/Stable
Classifier: Intended Audience :: Developers
Classifier: License :: OSI Approved :: GNU General Public License v3 (GPLv3)
Classifier: Operating System :: Unix
Classifier: Operating System :: POSIX
Classifier: Operating System :: Microsoft :: Windows
Classifier: Programming Language :: Python
Classifier: Programming Language :: Python :: 2.7
Classifier: Programming Language :: Python :: 2 :: Only
Classifier: Programming Language :: Python :: Implementation :: CPython
Classifier: Programming Language :: Python :: Implementation :: PyPy
Classifier: Topic :: Utilities
Requires-Dist: six
Requires-Dist: click
Requires-Dist: tabletext
Requires-Dist: eyed3 (<0.8.0)
Requires-Dist: unidecode
Requires-Dist: flask
